<annotation>
	<folder>PUBG</folder>
	<filename>38.jpg</filename>
	<path>C:\Users\amishra3\Desktop\HACKS\PUBG\38.jpg</path>
	<source>
		<database>Unknown</database>
	</source>
	<size>
		<width>640</width>
		<height>360</height>
		<depth>3</depth>
	</size>
	<segmented>0</segmented>
	<object>
		<name>Player</name>
		<pose>Unspecified</pose>
		<truncated>0</truncated>
		<difficult>0</difficult>
		<bndbox>
			<xmin>263</xmin>
			<ymin>46</ymin>
			<xmax>373</xmax>
			<ymax>311</ymax>
		</bndbox>
	</object>
</annotation>
